uprate/__init__.py
uprate/_sync.py
uprate/_utils.py
uprate/bucket.py
uprate/decorators.py
uprate/errors.py
uprate/py.typed
uprate/rate.py
uprate/ratelimit.py
uprate/store.py
uprate-0.3.dist-info/LICENSE
uprate-0.3.dist-info/WHEEL
uprate-0.3.dist-info/METADATA
uprate-0.3.dist-info/RECORD
