Metadata-Version: 2.1
Name: uprate
Version: 0.3
Summary: Ratelimits. Dumbified. A fully typed, simple ratelimit library.
Home-page: https://github.com/WizzyGeek/uprate#readme
License: MIT
Keywords: ratelimits,limits,ratelimit
Author: WizzyGeek
Author-email: ojasscoding@gmail.com
Requires-Python: >=3.9,<4.0
Classifier: Development Status :: 5 - Production/Stable
Classifier: License :: OSI Approved :: MIT License
Classifier: Programming Language :: Python :: 3
Classifier: Programming Language :: Python :: 3.10
Classifier: Programming Language :: Python :: 3.9
Classifier: Topic :: Software Development :: Libraries :: Python Modules
Classifier: Typing :: Typed
Provides-Extra: docs
Requires-Dist: Sphinx (>=4.1.1,<5.0.0); extra == "docs"
Requires-Dist: furo (>=2021.7.5-beta.38,<2022.0.0); extra == "docs"
Requires-Dist: myst-parser (>=0.15.1,<0.16.0); extra == "docs"
Requires-Dist: sphinx-copybutton (>=0.4.0,<0.5.0); extra == "docs"
Project-URL: Bug Tracker, https://github.com/WizzyGeek/uprate/issues
Project-URL: Documentation, https://uprate.readthedocs.io/en/latest/
Project-URL: Discord, https://discord.gg/udmdsFk6Yx
Project-URL: Repository, https://github.com/WizzyGeek/uprate
